examples/PyKinectBodyGame.py
examples/__init__.py
pykinect2/PyKinectRuntime.py
pykinect2/PyKinectV2.py
pykinect2/__init__.py
pykinect2-0.1.0.dist-info/DESCRIPTION.rst
pykinect2-0.1.0.dist-info/METADATA
pykinect2-0.1.0.dist-info/metadata.json
pykinect2-0.1.0.dist-info/RECORD
pykinect2-0.1.0.dist-info/top_level.txt
pykinect2-0.1.0.dist-info/WHEEL
